pysmells/__init__.py
pysmells/analyze.py
pysmells/pysmells.py
test/__init__.py
test/programa1/__init__.py
test/programa1/badcode1.py
test/programa2/__init__.py
test/programa2/badcode2.py
pysmells-1.0.11.dist-info/LICENSE
pysmells-1.0.11.dist-info/METADATA
pysmells-1.0.11.dist-info/WHEEL
pysmells-1.0.11.dist-info/entry_points.txt
pysmells-1.0.11.dist-info/top_level.txt
pysmells-1.0.11.dist-info/RECORD
